rock_paper_scissors/__init__.py
rock_paper_scissors/client.py
rock_paper_scissors/config.py
rock_paper_scissors/exceptions.py
rock_paper_scissors/game.py
rock_paper_scissors/logging_setup.py
rock_paper_scissors/py.typed
rock_paper_scissors_test-0.1.2.dist-info/METADATA
rock_paper_scissors_test-0.1.2.dist-info/WHEEL
rock_paper_scissors_test-0.1.2.dist-info/licenses/LICENSE
rock_paper_scissors_test-0.1.2.dist-info/RECORD
