Metadata-Version: 2.4
Name: rock-paper-scissors-test
Version: 0.1.2
Summary: A game of RPS
Project-URL: Homepage, https://github.com/filmingstudio/rock_paper_scissors
Project-URL: Repository, https://github.com/filmingstudio/rock_paper_scissors
Project-URL: Issues, https://github.com/filmingstudio/rock_paper_scissors/issues
Project-URL: Changelog, https://github.com/filmingstudio/rock_paper_scissors/blob/master/CHANGELOG.md
Author: Filming
License: Copyright (c) 2025 Filming
License-File: LICENSE
Keywords: python,python3
Classifier: Development Status :: 3 - Alpha
Classifier: Intended Audience :: Developers
Classifier: License :: OSI Approved :: MIT License
Classifier: Programming Language :: Python :: 3
Classifier: Programming Language :: Python :: 3.10
Classifier: Programming Language :: Python :: 3.11
Classifier: Programming Language :: Python :: 3.12
Classifier: Programming Language :: Python :: 3.13
Classifier: Programming Language :: Python :: 3.14
Classifier: Programming Language :: Python :: 3.15
Requires-Python: >=3.10
Requires-Dist: platformdirs>=4.4.0
Requires-Dist: pydantic-settings>=2.11.0
Provides-Extra: dev
Requires-Dist: commitizen>=4.8.3; extra == 'dev'
Requires-Dist: mypy>=1.16.1; extra == 'dev'
Requires-Dist: pre-commit>=4.2.0; extra == 'dev'
Requires-Dist: pytest-cov>=5.0.0; extra == 'dev'
Requires-Dist: pytest>=8.0.0; extra == 'dev'
Requires-Dist: ruff>=0.12.1; extra == 'dev'
Requires-Dist: twine>=5.0.0; extra == 'dev'
